oap_rq
