Metadata-Version: 2.1
Name: oap-rq
Version: 0.0.6
Author: Caleb Carvalho
Author-email: caleb.carvalho@gmail.com
Provides-Extra: dev
License-File: LICENSE.txt
